LICENSE.md
MANIFEST.in
README.md
setup.py
opbeat_pyramid/__init__.py
opbeat_pyramid/__init___spec.py
opbeat_pyramid/subscribers.py
opbeat_pyramid/subscribers_spec.py
opbeat_pyramid/tweens.py
opbeat_pyramid/tweens_spec.py
opbeat_pyramid.egg-info/PKG-INFO
opbeat_pyramid.egg-info/SOURCES.txt
opbeat_pyramid.egg-info/dependency_links.txt
opbeat_pyramid.egg-info/not-zip-safe
opbeat_pyramid.egg-info/requires.txt
opbeat_pyramid.egg-info/top_level.txt