Metadata-Version: 1.1
Name: opbeat-pyramid
Version: 1.0.12
Summary: Provides opbeat instrumentation for your Pyramid projects.
Home-page: https://github.com/monokrome/opbeat_pyramid
Author: Bailey Stoner
Author-email: monokrome@monokro.me
License: MIT
Keywords: web pyramid pylons
Platform: UNKNOWN
Classifier: Programming Language :: Python
Classifier: Framework :: Pyramid
